[
  {
    "name": "Github",
    "icon": "/images/icon/github.png",
    "tip": "去 Github 看看",
    "url": "https://github.com/bob-bzh"
  },
  {
    "name": "BiliBili",
    "icon": "/images/icon/bilibili.png",
    "tip": "(゜-゜)つロ 干杯 ~",
    "url": "https://space.bilibili.com/431516846?spm_id_from=333.1007.0.0"
  },
  {
    "name": "QQ",
    "icon": "/images/icon/qq.png",
    "tip": "有什么事吗",
    "url": "https://res.abeim.cn/api/qq/?qq=2950253898"
  },
  {
    "name": "Twitter",
    "icon": "/images/icon/twitter.png",
    "tip": "你懂的 ~",
    "url": "https://twitter.com/baozh86019"
  },
  {
    "name": "Gitee",
    "icon": "/images/icon/gitee.png",
    "tip": "gitee",
    "url": "https://gitee.com/BoBOvO"
  },
  {
    "name": "TikTok",
    "icon": "/images/icon/tiktok.webp",
    "tip": "tiktiktok！",
    "url": "https://www.douyin.com/user/MS4wLjABAAAAWft4N_23VO_HHG02Z6HxP7hMGAl4P88AbzX8N23fwIGgJ_alu0en4JP-I0-iCIbe"
  }
]
